django_remake_migrations/__init__.py
django_remake_migrations/apps.py
django_remake_migrations/conf.py
django_remake_migrations/py.typed
django_remake_migrations/management/__init__.py
django_remake_migrations/management/commands/__init__.py
django_remake_migrations/management/commands/remakemigrations.py
django_remake_migrations-2.9.0.dist-info/licenses/LICENSE
django_remake_migrations-2.9.0.dist-info/METADATA
django_remake_migrations-2.9.0.dist-info/WHEEL
django_remake_migrations-2.9.0.dist-info/top_level.txt
django_remake_migrations-2.9.0.dist-info/RECORD
