Metadata-Version: 2.4
Name: django-remake-migrations
Version: 2.9.0
Summary: A Django admin command to recreate all migrations in a project.
Author-email: Bruno Alla <oss@browniebroke.com>
License-Expression: MIT
Project-URL: Bug Tracker, https://github.com/browniebroke/django-remake-migrations/issues
Project-URL: Changelog, https://github.com/browniebroke/django-remake-migrations/blob/main/CHANGELOG.md
Project-URL: documentation, https://django-remake-migrations.readthedocs.io
Project-URL: repository, https://github.com/browniebroke/django-remake-migrations
Classifier: Development Status :: 2 - Pre-Alpha
Classifier: Framework :: Django
Classifier: Framework :: Django :: 4.2
Classifier: Framework :: Django :: 5.0
Classifier: Framework :: Django :: 5.1
Classifier: Framework :: Django :: 5.2
Classifier: Framework :: Django :: 6.0
Classifier: Intended Audience :: Developers
Classifier: Natural Language :: English
Classifier: Operating System :: OS Independent
Classifier: Programming Language :: Python :: 3 :: Only
Classifier: Programming Language :: Python :: 3.10
Classifier: Programming Language :: Python :: 3.11
Classifier: Programming Language :: Python :: 3.12
Classifier: Programming Language :: Python :: 3.13
Classifier: Programming Language :: Python :: 3.14
Classifier: Topic :: Software Development :: Libraries
Requires-Python: >=3.10
License-File: LICENSE
Requires-Dist: django>=4.2
Dynamic: license-file
